Metadata-Version: 2.1
Name: AIauxiliar
Version: 1.0
Summary: Há muitos e muitos anos, há tantos anos quanto o número de estrelas no céu, o Paraíso Celeste
Author: Guilherme Menezes
Author-email: guilherme.menezes@outlook.com
Keywords: AI,auxiliar,creating AI,creating Inteligence
License-File: license.txt
